netcdftime/__init__.py
netcdftime/_netcdftime.cpython-36m-darwin.so
netcdftime/netcdftime.cpython-36m-darwin.so
netcdftime-1.0.0a2.dist-info/DESCRIPTION.rst
netcdftime-1.0.0a2.dist-info/METADATA
netcdftime-1.0.0a2.dist-info/RECORD
netcdftime-1.0.0a2.dist-info/WHEEL
netcdftime-1.0.0a2.dist-info/metadata.json
netcdftime-1.0.0a2.dist-info/top_level.txt
