Metadata-Version: 2.0
Name: netcdftime
Version: 1.0.0a2
Summary: Time-handling functionality from netcdf4-python
Home-page: UNKNOWN
Author: Jeff Whitaker
Author-email: jeffrey.s.whitaker@noaa.gov
License: UNKNOWN
Platform: UNKNOWN
Requires-Dist: cython
Requires-Dist: numpy
